calligraphy_scripting/__init__.py
calligraphy_scripting/cli.py
calligraphy_scripting/data/header.py
calligraphy_scripting/parser.py
calligraphy_scripting/runner.py
calligraphy_scripting/transpiler.py
calligraphy_scripting/utils.py
calligraphy_scripting-1.2.1.dist-info/METADATA
calligraphy_scripting-1.2.1.dist-info/WHEEL
calligraphy_scripting-1.2.1.dist-info/entry_points.txt
calligraphy_scripting-1.2.1.dist-info/licenses/LICENSE
calligraphy_scripting-1.2.1.dist-info/RECORD
