Metadata-Version: 2.4
Name: calligraphy-scripting
Version: 1.2.1
Summary: A hybrid language for a modern approach to shell scripting
License: MIT
License-File: LICENSE
Keywords: scripting,calligraphy
Author: John Carter
Author-email: jfcarter2358@gmail.com
Requires-Python: >=3.8,<4.0
Classifier: License :: OSI Approved :: MIT License
Classifier: Programming Language :: Python :: 3
Classifier: Programming Language :: Python :: 3.8
Classifier: Programming Language :: Python :: 3.9
Classifier: Programming Language :: Python :: 3.10
Classifier: Programming Language :: Python :: 3.11
Classifier: Programming Language :: Python :: 3.12
Classifier: Programming Language :: Python :: 3.13
Classifier: Programming Language :: Python :: 3.14
Project-URL: Repository, https://github.com/jfcarter2358/calligraphy
